[
  {
    "region_id": "region_001",
    "page": 1,
    "label": "title",
    "bbox": [
      944,
      421,
      1619,
      507
    ],
    "reading_order": 1,
    "crop_file": "output/Stable_angina/crops/region_001_title.png"
  },
  {
    "region_id": "region_002",
    "page": 1,
    "label": "header_footer",
    "bbox": [
      82,
      614,
      538,
      719
    ],
    "reading_order": 2,
    "crop_file": "output/Stable_angina/crops/region_002_header_footer.png"
  },
  {
    "region_id": "region_003",
    "page": 1,
    "label": "text",
    "bbox": [
      624,
      624,
      1236,
      2015
    ],
    "reading_order": 3,
    "crop_file": "output/Stable_angina/crops/region_003_text.png"
  },
  {
    "region_id": "region_004",
    "page": 1,
    "label": "header_footer",
    "bbox": [
      1321,
      798,
      1391,
      1182
    ],
    "reading_order": 4,
    "crop_file": "output/Stable_angina/crops/region_004_header_footer.png"
  },
  {
    "region_id": "region_005",
    "page": 1,
    "label": "text",
    "bbox": [
      1410,
      608,
      2462,
      1087
    ],
    "reading_order": 5,
    "crop_file": "output/Stable_angina/crops/region_005_text.png"
  },
  {
    "region_id": "region_006",
    "page": 1,
    "label": "text",
    "bbox": [
      1423,
      1160,
      2446,
      1429
    ],
    "reading_order": 6,
    "crop_file": "output/Stable_angina/crops/region_006_text.png"
  },
  {
    "region_id": "region_007",
    "page": 1,
    "label": "text",
    "bbox": [
      1423,
      1511,
      2456,
      2025
    ],
    "reading_order": 7,
    "crop_file": "output/Stable_angina/crops/region_007_text.png"
  },
  {
    "region_id": "region_008",
    "page": 1,
    "label": "text",
    "bbox": [
      9,
      2063,
      2570,
      2450
    ],
    "reading_order": 8,
    "crop_file": "output/Stable_angina/crops/region_008_text.png"
  },
  {
    "region_id": "region_009",
    "page": 1,
    "label": "text",
    "bbox": [
      0,
      2450,
      2570,
      3011
    ],
    "reading_order": 9,
    "crop_file": "output/Stable_angina/crops/region_009_text.png"
  },
  {
    "region_id": "region_010",
    "page": 1,
    "label": "text",
    "bbox": [
      9,
      3017,
      779,
      3527
    ],
    "reading_order": 10,
    "crop_file": "output/Stable_angina/crops/region_010_text.png"
  },
  {
    "region_id": "region_011",
    "page": 1,
    "label": "text",
    "bbox": [
      868,
      3023,
      2548,
      3543
    ],
    "reading_order": 11,
    "crop_file": "output/Stable_angina/crops/region_011_text.png"
  },
  {
    "region_id": "region_012",
    "page": 1,
    "label": "header_footer",
    "bbox": [
      687,
      3559,
      1112,
      3625
    ],
    "reading_order": 12,
    "crop_file": "output/Stable_angina/crops/region_012_header_footer.png"
  },
  {
    "region_id": "region_013",
    "page": 1,
    "label": "text",
    "bbox": [
      3,
      3616,
      694,
      4243
    ],
    "reading_order": 13,
    "crop_file": "output/Stable_angina/crops/region_013_text.png"
  },
  {
    "region_id": "region_014",
    "page": 1,
    "label": "text",
    "bbox": [
      694,
      3632,
      1809,
      4247
    ],
    "reading_order": 14,
    "crop_file": "output/Stable_angina/crops/region_014_text.png"
  },
  {
    "region_id": "region_015",
    "page": 1,
    "label": "text",
    "bbox": [
      1835,
      3559,
      2526,
      4215
    ],
    "reading_order": 15,
    "crop_file": "output/Stable_angina/crops/region_015_text.png"
  },
  {
    "region_id": "region_016",
    "page": 1,
    "label": "text",
    "bbox": [
      9,
      4253,
      2564,
      4507
    ],
    "reading_order": 16,
    "crop_file": "output/Stable_angina/crops/region_016_text.png"
  },
  {
    "region_id": "region_017",
    "page": 1,
    "label": "text",
    "bbox": [
      9,
      4513,
      2564,
      4741
    ],
    "reading_order": 17,
    "crop_file": "output/Stable_angina/crops/region_017_text.png"
  }
]